limpyd/__init__.py
limpyd/collection.py
limpyd/database.py
limpyd/exceptions.py
limpyd/fields.py
limpyd/indexes.py
limpyd/model.py
limpyd/utils.py
limpyd/contrib/__init__.py
limpyd/contrib/collection.py
limpyd/contrib/database.py
limpyd/contrib/indexes.py
limpyd/contrib/related.py
redis_limpyd-2.1.2.dist-info/LICENSE
redis_limpyd-2.1.2.dist-info/METADATA
redis_limpyd-2.1.2.dist-info/WHEEL
redis_limpyd-2.1.2.dist-info/top_level.txt
redis_limpyd-2.1.2.dist-info/zip-safe
redis_limpyd-2.1.2.dist-info/RECORD
