Metadata-Version: 2.1
Name: redis-limpyd
Version: 2.1.2
Summary: Limpyd provides an easy way to store objects in Redis, without losing the power and the control of the Redis API, in a limpid way, with just as abstraction as needed.
Home-page: https://github.com/limpyd/redis-limpyd
Author: Yohan Boniface
Author-email: yb@enix.org
Maintainer: Stephane "Twidi" Angel
Maintainer-email: s.angel@twidi.com
License: WTFPL
Keywords: redis,orm
Platform: any
Classifier: Development Status :: 5 - Production/Stable
Classifier: Intended Audience :: Developers
Classifier: Operating System :: OS Independent
Classifier: Topic :: Database
Classifier: Topic :: Software Development :: Libraries :: Python Modules
Classifier: Programming Language :: Python
Classifier: Programming Language :: Python :: 2
Classifier: Programming Language :: Python :: 2.7
Classifier: Programming Language :: Python :: 3
Classifier: Programming Language :: Python :: 3.5
Classifier: Programming Language :: Python :: 3.6
Classifier: Programming Language :: Python :: 3.7
Classifier: Programming Language :: Python :: 3.8
Classifier: Programming Language :: Python :: Implementation :: CPython
Classifier: Programming Language :: Python :: Implementation :: PyPy
Requires-Python: !=3.0.*,!=3.1.*,!=3.2.*,!=3.3.*,!=3.4.*,>=2.7
Requires-Dist: redis (>=3)
Requires-Dist: future
Provides-Extra: doc
Requires-Dist: Sphinx ; extra == 'doc'
Requires-Dist: sphinx-rtd-theme ; extra == 'doc'
Provides-Extra: test
Requires-Dist: six ; extra == 'test'
